duqtools/__init__.py
duqtools/_click_opt_groups.py
duqtools/_logging_utils.py
duqtools/_plot_utils.py
duqtools/_types.py
duqtools/api.py
duqtools/apply_model.py
duqtools/cleanup.py
duqtools/cli.py
duqtools/create.py
duqtools/dash.py
duqtools/duqmap.py
duqtools/init.py
duqtools/list_variables.py
duqtools/matrix_samplers.py
duqtools/merge.py
duqtools/operations.py
duqtools/plot.py
duqtools/setup.py
duqtools/status.py
duqtools/submit.py
duqtools/sync_prominence.py
duqtools/utils.py
duqtools/config/__init__.py
duqtools/config/_config.py
duqtools/config/_schema_create.py
duqtools/config/_schema_root.py
duqtools/config/_variables.py
duqtools/dashboard/Plotting.py
duqtools/dashboard/_shared.py
duqtools/dashboard/readme.md
duqtools/dashboard/requirements.txt
duqtools/dashboard/pages/1_Merging.py
duqtools/data/duqtools.yaml
duqtools/data/jetto_lookup.json
duqtools/data/logo.png
duqtools/data/variables.yaml
duqtools/data/variables_ids2jetto.yaml
duqtools/ids/__handle.py
duqtools/ids/__init__.py
duqtools/ids/_apply_model.py
duqtools/ids/_copy.py
duqtools/ids/_handle.py
duqtools/ids/_hdf5handle.py
duqtools/ids/_imas.py
duqtools/ids/_mapping.py
duqtools/ids/_mdsplushandle.py
duqtools/ids/_merge.py
duqtools/ids/_schema.py
duqtools/large_scale_validation/__init__.py
duqtools/large_scale_validation/cli.py
duqtools/large_scale_validation/create.py
duqtools/large_scale_validation/merge.py
duqtools/large_scale_validation/setup.py
duqtools/large_scale_validation/status.py
duqtools/large_scale_validation/submit.py
duqtools/models/__init__.py
duqtools/models/_job.py
duqtools/models/_locations.py
duqtools/models/_run.py
duqtools/schema/__init__.py
duqtools/schema/_basemodel.py
duqtools/schema/_dimensions.py
duqtools/schema/_ranges.py
duqtools/schema/matrix_samplers.py
duqtools/systems/__init__.py
duqtools/systems/base_system.py
duqtools/systems/jintrac.py
duqtools/systems/models.py
duqtools/systems/jetto/__init__.py
duqtools/systems/jetto/_batchfile.py
duqtools-3.1.6.dist-info/LICENSE
duqtools-3.1.6.dist-info/METADATA
duqtools-3.1.6.dist-info/WHEEL
duqtools-3.1.6.dist-info/entry_points.txt
duqtools-3.1.6.dist-info/top_level.txt
duqtools-3.1.6.dist-info/RECORD
