Metadata-Version: 2.1
Name: duqtools
Version: 3.1.6
Summary: Dynamic uncertainty quantification for Tokamak reactor simulations modelling
Author: Victor Azizi, Aaron Ho
Author-email: Stef Smeets <s.smeets@esciencecenter.nl>
License: Apache 2.0 License
Project-URL: homepage, https://github.com/duqtools/duqtools
Project-URL: issues, https://github.com/duqtools/duqtools/issues
Project-URL: documentation, https://duqtools.readthedocs.io
Project-URL: changelog, https://github.com/duqtools/duqtools/releases
Keywords: modelling,uncertainty-quantification,tokamak,fusion-reactor
Classifier: Development Status :: 3 - Alpha
Classifier: Intended Audience :: Developers
Classifier: Intended Audience :: Science/Research
Classifier: License :: OSI Approved :: Apache Software License
Classifier: Natural Language :: English
Classifier: Operating System :: POSIX :: Linux
Classifier: Programming Language :: Python :: 3
Classifier: Programming Language :: Python :: 3.9
Classifier: Programming Language :: Python :: 3.10
Classifier: Programming Language :: Python :: 3.11
Classifier: Topic :: Scientific/Engineering
Requires-Python: >=3.9
License-File: LICENSE
Requires-Dist: altair>=5.0
Requires-Dist: click
Requires-Dist: gitpython
Requires-Dist: imas2xarray>=0.2.0
Requires-Dist: jetto-tools>=2.0.0
Requires-Dist: jinja2>=3.0
Requires-Dist: numpy
Requires-Dist: pandas
Requires-Dist: pydantic>=2.0
Requires-Dist: pydantic-yaml>=1.0
Requires-Dist: scipy>=1.09
Requires-Dist: streamlit>=1.38
Requires-Dist: tqdm
Requires-Dist: typing-extensions>=4.13.1
Requires-Dist: xarray
Requires-Dist: importlib-resources; python_version < "3.10"
Provides-Extra: develop
Requires-Dist: bump-my-version; extra == "develop"
Requires-Dist: ruff; extra == "develop"
Requires-Dist: pre-commit; extra == "develop"
Requires-Dist: yapf; extra == "develop"
Requires-Dist: mypy; extra == "develop"
Requires-Dist: coverage[toml]; extra == "develop"
Requires-Dist: pytest; extra == "develop"
Requires-Dist: pytest-dependency; extra == "develop"
Provides-Extra: docs
Requires-Dist: jinja2; extra == "docs"
Requires-Dist: markdown-include; extra == "docs"
Requires-Dist: mkdocs; extra == "docs"
Requires-Dist: mkdocs-click; extra == "docs"
Requires-Dist: mkdocs-gen-files; extra == "docs"
Requires-Dist: mkdocs-material; extra == "docs"
Requires-Dist: mkdocstrings[python]; extra == "docs"
Requires-Dist: mknotebooks; extra == "docs"
Provides-Extra: imas
Requires-Dist: imas; extra == "imas"
Provides-Extra: publishing
Requires-Dist: twine; extra == "publishing"
Requires-Dist: wheel; extra == "publishing"
Requires-Dist: build; extra == "publishing"
